ChineseNER/__init__.py
ChineseNER/crf.py
ChineseNER/dataset.py
ChineseNER/model.py
ChineseNER/static_record.py
ChineseNER/tagSchemeConverter.py
ChineseNER/train.py
ChineseNER/use_model.py
ChineseNER/utils.py
ChineseNER/data/dh_msra.txt
ChineseNER/data/msra.txt
ChineseNER/data/msra_test.txt
ChineseNER/data/msra_train.txt
ChineseNER/model/lstmTrue
ChineseNER-0.1.dist-info/LICENSE
ChineseNER-0.1.dist-info/METADATA
ChineseNER-0.1.dist-info/WHEEL
ChineseNER-0.1.dist-info/top_level.txt
ChineseNER-0.1.dist-info/RECORD
